sgl/__init__.py
sgl/binary.txt
sglang_kernel-0.0.7.dist-info/licenses/LICENSE
sglang_kernel-0.0.7.dist-info/METADATA
sglang_kernel-0.0.7.dist-info/WHEEL
sglang_kernel-0.0.7.dist-info/top_level.txt
sglang_kernel-0.0.7.dist-info/RECORD
