Metadata-Version: 2.4
Name: sglang-kernel
Version: 0.0.7
Summary: Kernel Library for SGLang
License:                                  Apache License
Project-URL: Homepage, https://github.com/sgl-project/sglang/tree/main/sgl-kernel
Project-URL: Bug Tracker, https://github.com/sgl-project/sglang/issues
Classifier: Programming Language :: Python :: 3
Classifier: License :: OSI Approved :: Apache Software License
Classifier: Environment :: GPU :: NVIDIA CUDA
Requires-Python: >=3.10
License-File: LICENSE
Dynamic: license-file
